vibe_client/__init__.py
vibe_client/client.py
vibe_client/config.py
vibe_client/deserialize.py
vibe_client/models.py
vibe_client/serialize.py
vibe_client/_private/__init__.py
vibe_client/_private/schemas.py
vibe_client-0.1.2.dist-info/METADATA
vibe_client-0.1.2.dist-info/WHEEL
vibe_client-0.1.2.dist-info/RECORD
