Metadata-Version: 2.4
Name: vibe_client
Version: 0.1.2
Summary: vibe client
License: Apache-2.0
Keywords: smithy,vibe
Classifier: Development Status :: 2 - Pre-Alpha
Classifier: Intended Audience :: Developers
Classifier: Intended Audience :: System Administrators
Classifier: License :: OSI Approved :: Apache Software License
Classifier: Natural Language :: English
Classifier: Programming Language :: Python
Classifier: Programming Language :: Python :: 3
Classifier: Programming Language :: Python :: 3 :: Only
Classifier: Programming Language :: Python :: 3.12
Classifier: Programming Language :: Python :: 3.13
Requires-Python: >=3.12
Requires-Dist: smithy-core<0.1.0
Requires-Dist: smithy-http[aiohttp]<0.1.0
Requires-Dist: smithy-json<0.1.0
Provides-Extra: docs
Requires-Dist: pydata-sphinx-theme>=0.16.1; extra == 'docs'
Requires-Dist: sphinx>=8.2.3; extra == 'docs'
Provides-Extra: tests
Requires-Dist: pytest-asyncio<0.21.0,>=0.20.3; extra == 'tests'
Requires-Dist: pytest<8.0.0,>=7.2.0; extra == 'tests'
